Metadata-Version: 1.0
Name: nerf
Version: 0.1.4
Summary: Second test version of NERF
Home-page: UNKNOWN
Author: Yue Zhang
Author-email: yue.zhang@lih.lu
License: UNKNOWN
Keywords: random forest,interpretation
Platform: any
